meinheld-0.6.1.dist-info/RECORD
meinheld-0.6.1.dist-info/METADATA
meinheld-0.6.1.dist-info/WHEEL
meinheld-0.6.1.dist-info/top_level.txt
meinheld-0.6.1.dist-info/metadata.json
meinheld-0.6.1.dist-info/entry_points.txt
meinheld-0.6.1.dist-info/DESCRIPTION.rst
meinheld/server.cpython-36m-x86_64-linux-gnu.so
meinheld/__init__.py
meinheld/gmeinheld.py
meinheld/websocket.py
meinheld/patch.py
meinheld/msocket.py
meinheld/mlogging.py
meinheld/middleware.py
meinheld/common.py
