Metadata-Version: 1.1
Name: meinheld
Version: 0.6.1
Summary: High performance asynchronous Python WSGI Web Server
Home-page: http://meinheld.org
Author: yutaka matsubara
Author-email: yutaka.matsubara@gmail.com
License: BSD
Platform: Linux
Platform: BSD
Platform: Darwin
Classifier: Development Status :: 4 - Beta
Classifier: Environment :: Web Environment
Classifier: Intended Audience :: Developers
Classifier: License :: OSI Approved :: BSD License
Classifier: Operating System :: POSIX :: Linux
Classifier: Operating System :: MacOS :: MacOS X
Classifier: Operating System :: POSIX :: BSD :: FreeBSD
Classifier: Programming Language :: C
Classifier: Programming Language :: Python
Classifier: Programming Language :: Python :: 3
Classifier: Topic :: Internet :: WWW/HTTP :: WSGI :: Server
